mcmc_diagnostics/__init__.py
mcmc_diagnostics/ar_model.py
mcmc_diagnostics/cramer_von_mises_test.py
mcmc_diagnostics/effective_sample_size.py
mcmc_diagnostics-0.1.dist-info/LICENSE
mcmc_diagnostics-0.1.dist-info/METADATA
mcmc_diagnostics-0.1.dist-info/WHEEL
mcmc_diagnostics-0.1.dist-info/top_level.txt
mcmc_diagnostics-0.1.dist-info/RECORD
