Metadata-Version: 2.1
Name: mcmc-diagnostics
Version: 0.1
Summary: Python analogue of the R coda package
Home-page: https://github.com/aki-nishimura/mcmc-diagnostics
Author: Akihiko (Aki) Nishimura
Author-email: akihiko4@ucla.edu
License: MIT
Platform: UNKNOWN
